libsm/__init__.py
libsm/func.py
libsm/sm.py
libsm/value.py
libsm-0.1.0.dist-info/LICENSE
libsm-0.1.0.dist-info/METADATA
libsm-0.1.0.dist-info/WHEEL
libsm-0.1.0.dist-info/top_level.txt
libsm-0.1.0.dist-info/RECORD
